imgstore/__init__.py
imgstore/align.py
imgstore/apps.py
imgstore/configuration.py
imgstore/constants.py
imgstore/index.py
imgstore/interface.py
imgstore/ui.py
imgstore/util.py
imgstore/compat/__init__.py
imgstore/compat/constants.py
imgstore/compat/index.py
imgstore/compat/stores.py
imgstore/compat/util.py
imgstore/stores/__init__.py
imgstore/stores/core.py
imgstore/stores/directory.py
imgstore/stores/multi.py
imgstore/stores/video.py
imgstore/stores/base/__init__.py
imgstore/stores/base/core.py
imgstore/stores/base/read.py
imgstore/stores/base/write.py
imgstore/stores/utils/__init__.py
imgstore/stores/utils/datetime.py
imgstore/stores/utils/formats.py
imgstore/stores/utils/logging.py
imgstore/stores/utils/path.py
imgstore/stores/utils/ranges.py
imgstore/stores/utils/mixins/__init__.py
imgstore/stores/utils/mixins/cm.py
imgstore/stores/utils/mixins/cv2.py
imgstore/stores/utils/mixins/extra_data.py
imgstore/stores/utils/mixins/extract.py
imgstore/stores/utils/mixins/frame_number.py
imgstore/stores/utils/mixins/get.py
imgstore/stores/utils/mixins/index.py
imgstore/stores/utils/mixins/multi.py
imgstore/stores/utils/mixins/serialize.py
imgstore/tests/__init__.py
imgstore/tests/test_crossindex.py
imgstore/tests/test_imgstore.py
imgstore/tests/test_index.py
imgstore/tests/test_multistore.py
imgstore/tests/test_serialize.py
imgstore/tests/test_util.py
imgstore_shaliulab-0.4.15.dist-info/LICENSE.txt
imgstore_shaliulab-0.4.15.dist-info/METADATA
imgstore_shaliulab-0.4.15.dist-info/WHEEL
imgstore_shaliulab-0.4.15.dist-info/entry_points.txt
imgstore_shaliulab-0.4.15.dist-info/top_level.txt
imgstore_shaliulab-0.4.15.dist-info/RECORD
