Metadata-Version: 2.1
Name: imgstore-shaliulab
Version: 0.4.15
Summary: IMGStore houses your video frames
Home-page: https://github.com/shaliulab/imgstore
Author: John Stowers, Santi Villalba, Antonio Ortega
Author-email: john@loopbio.com, santi@loopbio.com, antonio.ortega@kuleuven.be
License: BSD 3 clause
Classifier: Intended Audience :: Science/Research
Classifier: Intended Audience :: Developers
Classifier: Topic :: Software Development
Classifier: Topic :: Scientific/Engineering
Classifier: License :: OSI Approved
Classifier: Programming Language :: Python :: 2
Classifier: Programming Language :: Python :: 2.7
Classifier: Programming Language :: Python :: 3
Classifier: Programming Language :: Python :: 3.4
Classifier: Programming Language :: Python :: 3.5
Classifier: Programming Language :: Python :: 3.6
License-File: LICENSE.txt
Requires-Dist: numpy
Requires-Dist: pandas
Requires-Dist: pyyaml
Requires-Dist: pytz
Requires-Dist: tzlocal
Requires-Dist: python-dateutil
Requires-Dist: confapp-shaliulab (==1.1.13)
Requires-Dist: codetiming
Provides-Extra: bloscpack
Requires-Dist: bloscpack ; extra == 'bloscpack'
Provides-Extra: cv2cuda
Requires-Dist: cv2cuda (>=1.0.4) ; extra == 'cv2cuda'
